shellsh/__init__.py
shellsh/shellsh.py
shellsh-0.4.0.dist-info/licenses/LICENSE
shellsh-0.4.0.dist-info/METADATA
shellsh-0.4.0.dist-info/WHEEL
shellsh-0.4.0.dist-info/top_level.txt
shellsh-0.4.0.dist-info/RECORD
