Metadata-Version: 2.4
Name: shellsh
Version: 0.4.0
Summary: A Python library for managing persistent shell sessions programmatically
Home-page: https://github.com/yourusername/shellsh
Author: Saturnino Adrales
Author-email: Saturnino Adrales <your.email@example.com>
License: MIT
Project-URL: Homepage, https://github.com/yourusername/shellsh
Project-URL: Repository, https://github.com/yourusername/shellsh
Project-URL: Issues, https://github.com/yourusername/shellsh/issues
Keywords: shell,subprocess,terminal,pty,automation
Classifier: Development Status :: 3 - Alpha
Classifier: Intended Audience :: Developers
Classifier: License :: OSI Approved :: MIT License
Classifier: Operating System :: POSIX
Classifier: Operating System :: POSIX :: Linux
Classifier: Operating System :: MacOS
Classifier: Programming Language :: Python :: 3
Classifier: Programming Language :: Python :: 3.7
Classifier: Programming Language :: Python :: 3.8
Classifier: Programming Language :: Python :: 3.9
Classifier: Programming Language :: Python :: 3.10
Classifier: Programming Language :: Python :: 3.11
Classifier: Programming Language :: Python :: 3.12
Classifier: Topic :: Software Development :: Libraries :: Python Modules
Classifier: Topic :: System :: Shells
Requires-Python: >=3.7
License-File: LICENSE
Dynamic: author
Dynamic: home-page
Dynamic: license-file
Dynamic: requires-python
